{"cameraMode":{"drawMode":0,"name":"Shaded","section":"Shading Mode"},"sceneLighting":true,"audioPlay":false,"sceneViewState":{"m_AlwaysRefresh":false,"showFog":true,"showSkybox":true,"showFlares":true,"showImageEffects":true,"showParticleSystems":true,"showVisualEffectGraphs":true,"m_FxEnabled":true},"in2DMode":false,"pivot":{"x":-4.571300983428955,"y":-6.180668830871582,"z":-27.80889320373535},"rotation":{"x":0.623245894908905,"y":-0.001170600880868733,"z":0.0009385466109961271,"w":0.7820109724998474},"size":9.933317184448243,"orthographic":false}